{
  "project_info": {
    "project_number": "651956685170",
    "firebase_url": "https://fluttershare-c3bf4.firebaseio.com",
    "project_id": "fluttershare-c3bf4",
    "storage_bucket": "fluttershare-c3bf4.appspot.com"
  },
  "client": [
    {
      "client_info": {
        "mobilesdk_app_id": "1:651956685170:android:f44200f281eebd133a35eb",
        "android_client_info": {
          "package_name": "com.vsa.fluttershare"
        }
      },
      "oauth_client": [
        {
          "client_id": "651956685170-7mpmu8bdgicgjvfhvraqiuvn22v5o605.apps.googleusercontent.com",
          "client_type": 1,
          "android_info": {
            "package_name": "com.vsa.fluttershare",
            "certificate_hash": "bd6ea38864049253bc1575f522810fbcd68e8c6a"
          }
        },
        {
          "client_id": "651956685170-6ahmclthpv88vosp8eju1lf9gqo0icv8.apps.googleusercontent.com",
          "client_type": 3
        }
      ],
      "api_key": [
        {
          "current_key": "AIzaSyDT1O9YFj_JLTmxR_pC9u5ouYVzGBAlzPQ"
        }
      ],
      "services": {
        "appinvite_service": {
          "other_platform_oauth_client": [
            {
              "client_id": "651956685170-6ahmclthpv88vosp8eju1lf9gqo0icv8.apps.googleusercontent.com",
              "client_type": 3
            }
          ]
        }
      }
    }
  ],
  "configuration_version": "1"
}